pineflow/vector_stores/elasticsearch/__init__.py
pineflow/vector_stores/elasticsearch/base.py
pineflow_vector_stores_elasticsearch-0.7.1.dist-info/METADATA
pineflow_vector_stores_elasticsearch-0.7.1.dist-info/WHEEL
pineflow_vector_stores_elasticsearch-0.7.1.dist-info/RECORD
